ark_operator/__init__.py
ark_operator/py.typed
ark_operator-0.1.4.dist-info/METADATA
ark_operator-0.1.4.dist-info/WHEEL
ark_operator-0.1.4.dist-info/licenses/LICENSE
ark_operator-0.1.4.dist-info/RECORD
