Metadata-Version: 2.4
Name: ark-operator
Version: 0.1.4
Summary: K8s operator for managing ARK server clusters
Author-email: Christopher Bailey <cbailey@mort.is>
Maintainer-email: Christopher Bailey <cbailey@mort.is>
License: # Functional Source License, Version 1.1, MIT Future License
License-File: LICENSE
Classifier: Development Status :: 2 - Pre-Alpha
Classifier: Framework :: AsyncIO
Classifier: Intended Audience :: Developers
Classifier: Intended Audience :: System Administrators
Classifier: License :: Free For Educational Use
Classifier: License :: Free For Home Use
Classifier: License :: Free for non-commercial use
Classifier: License :: Other/Proprietary License
Classifier: Programming Language :: Python :: 3
Classifier: Programming Language :: Python :: 3.10
Classifier: Programming Language :: Python :: 3.11
Classifier: Programming Language :: Python :: 3.12
Classifier: Programming Language :: Python :: 3.13
Classifier: Programming Language :: Python :: 3.14
Classifier: Topic :: Games/Entertainment
Classifier: Topic :: System :: Systems Administration
Requires-Python: >=3.10
Requires-Dist: kopf
Provides-Extra: dev
Requires-Dist: build; extra == 'dev'
Requires-Dist: coverage[toml]; extra == 'dev'
Requires-Dist: hatch; extra == 'dev'
Requires-Dist: lxml; extra == 'dev'
Requires-Dist: mypy; extra == 'dev'
Requires-Dist: pytest; extra == 'dev'
Requires-Dist: pytest-asyncio; extra == 'dev'
Requires-Dist: pytest-cov; extra == 'dev'
Requires-Dist: pytest-env; extra == 'dev'
Requires-Dist: pytest-timeout; extra == 'dev'
Requires-Dist: pytest-xdist[psutil]; extra == 'dev'
Requires-Dist: python-dotenv; extra == 'dev'
Requires-Dist: ruff; extra == 'dev'
Requires-Dist: twine; extra == 'dev'
